PappaPronta/__init__.py
PappaPronta/__main__.py
PappaPronta/core/__init__.py
PappaPronta/core/base.py
PappaPronta/core/root_path.py
PappaPronta/core/setup_path.py
PappaPronta/creator/__init__.py
PappaPronta/creator/creator.py
PappaPronta/events/__init__.py
PappaPronta/events/csound_event.py
PappaPronta/events/event.py
PappaPronta/patterns/__init__.py
PappaPronta/patterns/all_patterns.py
PappaPronta/patterns/auto_sequence.py
PappaPronta/patterns/constant.py
PappaPronta/patterns/expon.py
PappaPronta/patterns/function.py
PappaPronta/patterns/linear.py
PappaPronta/patterns/pattern.py
PappaPronta/patterns/sequence.py
PappaPronta/patterns/pitch/__init__.py
PappaPronta/patterns/pitch/chromatic.py
PappaPronta/patterns/pitch/grisey.py
PappaPronta/patterns/pitch/sieve.py
PappaPronta/voices/__init__.py
PappaPronta/voices/voice.py
test/__init__.py
test/context.py
PappaPronta-0.0.1.dist-info/LICENSE
PappaPronta-0.0.1.dist-info/METADATA
PappaPronta-0.0.1.dist-info/WHEEL
PappaPronta-0.0.1.dist-info/top_level.txt
PappaPronta-0.0.1.dist-info/RECORD
