Metadata-Version: 2.1
Name: PappaPronta
Version: 0.0.1
Summary: PappaPronta is a library of readymade stereotyped musical objects for lazy students to produce ugly electronic music.
Home-page: https://git.smerm.org/SMERM/PappaPronta-python
Author: Nicola Bernardini
Author-email: nic.bern@tiscali.it
License: UNKNOWN
Project-URL: Source Code, https://git.smerm.org/SMERM/PappaPronta-python
Keywords: stupid electronic music composition readymade stereotype dummy easy idiot
Platform: UNKNOWN
Classifier: License :: OSI Approved :: GNU General Public License v3 or later (GPLv3+)
Requires-Python: >=3.7
